rocket/__init__.py
rocket/rocket.py
baidar_rocket-1.0.1.dist-info/LICENSE.txt
baidar_rocket-1.0.1.dist-info/METADATA
baidar_rocket-1.0.1.dist-info/WHEEL
baidar_rocket-1.0.1.dist-info/top_level.txt
baidar_rocket-1.0.1.dist-info/RECORD
