Metadata-Version: 2.1
Name: baidar-rocket
Version: 1.0.1
Summary: An awesome package that does something
Home-page: http://pypi.python.org/pypi/baidar-rocket/
Author: baidar samir
Author-email: s.baidar@esi-sba.dz
License: LICENSE.txt
License-File: LICENSE.txt
Requires-Dist: baidar-rocket
